random_ip_generator/IP2LOCATION-LITE-DB1.CSV
random_ip_generator/__init__.py
random_ip_generator/main.py
random_ip_generator-0.2.0.dist-info/LICENSE
random_ip_generator-0.2.0.dist-info/METADATA
random_ip_generator-0.2.0.dist-info/WHEEL
random_ip_generator-0.2.0.dist-info/entry_points.txt
random_ip_generator-0.2.0.dist-info/top_level.txt
random_ip_generator-0.2.0.dist-info/RECORD
