Metadata-Version: 2.2
Name: random-ip-generator
Version: 0.2.0
Summary: A package to generate random IP addresses for a given country code
Home-page: https://github.com/edde746/random-ip-generator
Author: edde746
License-File: LICENSE
Requires-Dist: ipaddress
Dynamic: author
Dynamic: description
Dynamic: description-content-type
Dynamic: home-page
Dynamic: requires-dist
Dynamic: summary
